fundb/__init__.py
fundb/adapters.py
fundb/cursor.py
fundb/database.py
fundb/jsonquery.py
fundb/lib.py
python_fundb-0.0.15.dist-info/LICENSE
python_fundb-0.0.15.dist-info/METADATA
python_fundb-0.0.15.dist-info/WHEEL
python_fundb-0.0.15.dist-info/top_level.txt
python_fundb-0.0.15.dist-info/RECORD
