Metadata-Version: 2.1
Name: python-fundb
Version: 0.0.15
Summary: FunDB: Hybrid Row-and-Document Oriented datastore leveraging SQL/RDBMS database: SQLite, MySQL, MariaDB, Postgresql 
Home-page: https://github.com/mardix/fundb
Author: Mardix
Author-email: mardix@blackdevhub.io
Classifier: Programming Language :: Python :: 3
Classifier: License :: OSI Approved :: MIT License
Classifier: Topic :: Database
Requires-Python: >=3.8.0
License-File: LICENSE
Requires-Dist: pymysql
Requires-Dist: sqlparams
Requires-Dist: DBUtils
